t_notes-0.1.1.data/scripts/t
t_notes-0.1.1.data/scripts/tnotes
t_notes-0.1.1.data/scripts/tt
tnotes/__init__.py
t_notes-0.1.1.dist-info/LICENSE
t_notes-0.1.1.dist-info/METADATA
t_notes-0.1.1.dist-info/WHEEL
t_notes-0.1.1.dist-info/top_level.txt
t_notes-0.1.1.dist-info/RECORD
