Metadata-Version: 2.1
Name: t-notes
Version: 0.1.1
Summary: Program for quick terminal-based notes
Home-page: http://github.com/oekshido/TNotes
Author: oekshido
Author-email: oekshido@gmail.com
License: MIT License
Keywords: notes terminal
Platform: UNKNOWN
Classifier: Development Status :: 3 - Alpha
Classifier: License :: OSI Approved :: MIT License
Classifier: Programming Language :: Python :: 3
Requires-Dist: pyyaml
Requires-Dist: readline
